raven_python_lambda/__about__.py
raven_python_lambda/__init__.py
raven_python_lambda/sqs_transport.py
raven_python_lambda/tests/__init__.py
raven_python_lambda/tests/conftest.py
raven_python_lambda/tests/test_config.py
raven_python_lambda/tests/test_decorator.py
raven_python_lambda/tests/test_sqs_transport.py
raven_python_lambda-0.1.10.dist-info/METADATA
raven_python_lambda-0.1.10.dist-info/RECORD
raven_python_lambda-0.1.10.dist-info/WHEEL
raven_python_lambda-0.1.10.dist-info/top_level.txt
