Metadata-Version: 2.1
Name: raven-python-lambda
Version: 0.1.10
Summary: Decorator for lambda sentry instrumentation.
Home-page: https://github.com/Netflix-Skunkworks/raven-python-lambda
Author: The developers
Author-email: oss@netflix.com
License: UNKNOWN
Keywords: aws,sentry,raven,lambda
Platform: UNKNOWN
Requires-Dist: boto3
Requires-Dist: raven (>=6.1.0)
Requires-Dist: psutil (>=5.2.2)
Provides-Extra: tests
Requires-Dist: pytest; extra == 'tests'
Requires-Dist: moto; extra == 'tests'
Requires-Dist: coveralls; extra == 'tests'
Requires-Dist: tox; extra == 'tests'
